dyphira/__init__.py
dyphira/openai.py
dyphira/runpod.py
dyphira/shadeform.py
dyphira-0.3.0.dist-info/LICENSE
dyphira-0.3.0.dist-info/METADATA
dyphira-0.3.0.dist-info/WHEEL
dyphira-0.3.0.dist-info/top_level.txt
dyphira-0.3.0.dist-info/RECORD
