Metadata-Version: 2.1
Name: dyphira
Version: 0.3.0
Summary: A Python package for interacting with OpenAI and runpod APIs via Dyphira proxy server.
Author-email: DivinerX <loc_yan@outlook.com>
License: MIT
Project-URL: Homepage, https://github.com/DivinerX/dyphira-python
Project-URL: Issues, https://github.com/DivinerX/dyphira-python/issues
Classifier: Programming Language :: Python :: 3
Classifier: Operating System :: OS Independent
Requires-Python: >=3.8
License-File: LICENSE
Requires-Dist: requests
